uun_iot_libledstrip/LedStrip.py
uun_iot_libledstrip/MeterStrip.py
uun_iot_libledstrip/__init__.py
uun_iot_libledstrip/data/sample_config.json
uun_iot_libledstrip/devices/DebugLedDev.py
uun_iot_libledstrip/devices/GPIODev.py
uun_iot_libledstrip/devices/I2CPixelDev.py
uun_iot_libledstrip/devices/LedDev.py
uun_iot_libledstrip/devices/NeopixelDev.py
uun_iot_libledstrip/devices/__init__.py
uun_iot_libledstrip-0.2.4.dist-info/LICENSE.md
uun_iot_libledstrip-0.2.4.dist-info/METADATA
uun_iot_libledstrip-0.2.4.dist-info/WHEEL
uun_iot_libledstrip-0.2.4.dist-info/top_level.txt
uun_iot_libledstrip-0.2.4.dist-info/RECORD
