Metadata-Version: 2.1
Name: uun-iot-libledstrip
Version: 0.2.4
Summary: Library for managing LED strips for infographic purposes.
Home-page: 
Author: (UUN) Tomáš Faikl
Author-email: tomas.faikl@unicornuniversity.net
Classifier: Programming Language :: Python :: 3
Classifier: License :: OSI Approved :: MIT License
Requires-Python: >=3.6
License-File: LICENSE.md
Provides-Extra: dev
Requires-Dist: colored (==1.4.4) ; extra == 'dev'
Provides-Extra: gpio
Requires-Dist: RPi.GPIO ; extra == 'gpio'
Provides-Extra: i2c
Requires-Dist: smbus2 ; extra == 'i2c'
Provides-Extra: neopixel
Requires-Dist: rpi-ws281x ; extra == 'neopixel'
Requires-Dist: adafruit-circuitpython-neopixel ; extra == 'neopixel'
Requires-Dist: adafruit-blinka ; extra == 'neopixel'
